database_convertion/AnalysisADT.py
database_convertion/__init__.py
database_convertion/__main__.py
database_convertion/base_dataset.py
database_convertion/bmykhaylivvv.py
database_convertion/file_operation.py
database_convertion/main.py
database_convertion/mykhailo_bondarenko.py
database_convertion/stefan.py
road_signs_db_convertion_michael-0.0.5.dist-info/LICENSE
road_signs_db_convertion_michael-0.0.5.dist-info/METADATA
road_signs_db_convertion_michael-0.0.5.dist-info/WHEEL
road_signs_db_convertion_michael-0.0.5.dist-info/top_level.txt
road_signs_db_convertion_michael-0.0.5.dist-info/RECORD
