Metadata-Version: 2.1
Name: road-signs-db-convertion-michael
Version: 0.0.5
Summary: A database collection & conversion package which performs analysis
Home-page: https://github.com/Road-Sign-UCU/Road-Sign-DB
Author: Road-Sign-UCU
Author-email: work.michael.2956@gmail.com
License: UNKNOWN
Project-URL: Bug Tracker, https://github.com/Road-Sign-UCU/Road-Sign-DB/issues
Platform: UNKNOWN
Classifier: Programming Language :: Python :: 3
Classifier: License :: OSI Approved :: MIT License
Classifier: Operating System :: OS Independent
Requires-Python: >=3.6
Requires-Dist: certifi (>=2020.12.5)
Requires-Dist: chardet (>=4.0.0)
Requires-Dist: cycler (>=0.10.0)
Requires-Dist: idna (>=2.10)
Requires-Dist: kiwisolver (>=1.3.1)
Requires-Dist: matplotlib (>=3.4.2)
Requires-Dist: numpy (>=1.20.3)
Requires-Dist: opencv-python (>=4.5.2.52)
Requires-Dist: Pillow (>=8.2.0)
Requires-Dist: pyparsing (>=2.4.7)
Requires-Dist: python-dateutil (>=2.8.1)
Requires-Dist: requests (>=2.25.1)
Requires-Dist: six (>=1.16.0)
Requires-Dist: urllib3 (>=1.26.4)
